setup.py
kaggle_cli/__init__.py
kaggle_cli/common.py
kaggle_cli/config.py
kaggle_cli/download.py
kaggle_cli/main.py
kaggle_cli/meta.py
kaggle_cli/submissions.py
kaggle_cli/submit.py
kaggle_cli.egg-info/PKG-INFO
kaggle_cli.egg-info/SOURCES.txt
kaggle_cli.egg-info/dependency_links.txt
kaggle_cli.egg-info/entry_points.txt
kaggle_cli.egg-info/namespace_packages.txt
kaggle_cli.egg-info/not-zip-safe
kaggle_cli.egg-info/pbr.json
kaggle_cli.egg-info/requires.txt
kaggle_cli.egg-info/top_level.txt